{"inputs":{"app/entry.server.tsx":{"bytes":577,"imports":[{"path":"@remix-run/react","kind":"import-statement","external":true},{"path":"react-dom/server","kind":"import-statement","external":true},{"path":"react/jsx-dev-runtime","kind":"import-statement","external":true}],"format":"esm"},"app/lib/hooks/useCart.ts":{"bytes":1600,"imports":[{"path":"zustand","kind":"import-statement","external":true},{"path":"zustand/middleware","kind":"import-statement","external":true}],"format":"esm"},"app/components/layout/SearchBar.tsx":{"bytes":1124,"imports":[{"path":"react","kind":"import-statement","external":true},{"path":"@remix-run/react","kind":"import-statement","external":true},{"path":"react/jsx-dev-runtime","kind":"import-statement","external":true}],"format":"esm"},"app/components/LanguageSwitcher.tsx":{"bytes":902,"imports":[{"path":"react-i18next","kind":"import-statement","external":true},{"path":"react","kind":"import-statement","external":true},{"path":"react/jsx-dev-runtime","kind":"import-statement","external":true}],"format":"esm"},"app/components/layout/Header.tsx":{"bytes":2975,"imports":[{"path":"app/lib/hooks/useCart.ts","kind":"import-statement","original":"~/lib/hooks/useCart"},{"path":"app/components/layout/SearchBar.tsx","kind":"import-statement","original":"./SearchBar"},{"path":"app/components/LanguageSwitcher.tsx","kind":"import-statement","original":"../LanguageSwitcher"},{"path":"react-i18next","kind":"import-statement","external":true},{"path":"react/jsx-dev-runtime","kind":"import-statement","external":true}],"format":"esm"},"app/styles/tailwind.css":{"bytes":32282,"imports":[]},"app/root.tsx":{"bytes":1181,"imports":[{"path":"@remix-run/node","kind":"import-statement","external":true},{"path":"@remix-run/react","kind":"import-statement","external":true},{"path":"app/components/layout/Header.tsx","kind":"import-statement","original":"~/components/layout/Header"},{"path":"app/styles/tailwind.css","kind":"import-statement","original":"~/styles/tailwind.css"},{"path":"react","kind":"import-statement","external":true},{"path":"react-i18next","kind":"import-statement","external":true},{"path":"react/jsx-dev-runtime","kind":"import-statement","external":true}],"format":"esm"},"app/components/rider/DeliveryHistory.tsx":{"bytes":3435,"imports":[{"path":"react/jsx-dev-runtime","kind":"import-statement","external":true}],"format":"esm"},"app/routes/rider.deliveries.tsx":{"bytes":668,"imports":[{"path":"@remix-run/node","kind":"import-statement","external":true},{"path":"@remix-run/react","kind":"import-statement","external":true},{"path":"app/components/rider/DeliveryHistory.tsx","kind":"import-statement","original":"~/components/rider/DeliveryHistory"},{"path":"react/jsx-dev-runtime","kind":"import-statement","external":true}],"format":"esm"},"app/components/admin/InventoryManagement.tsx":{"bytes":4697,"imports":[{"path":"react","kind":"import-statement","external":true},{"path":"react/jsx-dev-runtime","kind":"import-statement","external":true}],"format":"esm"},"app/routes/admin.inventory.tsx":{"bytes":887,"imports":[{"path":"@remix-run/node","kind":"import-statement","external":true},{"path":"@remix-run/react","kind":"import-statement","external":true},{"path":"app/components/admin/InventoryManagement.tsx","kind":"import-statement","original":"~/components/admin/InventoryManagement"},{"path":"react/jsx-dev-runtime","kind":"import-statement","external":true}],"format":"esm"},"app/components/admin/AdminDashboard.tsx":{"bytes":3667,"imports":[{"path":"@remix-run/react","kind":"import-statement","external":true},{"path":"react/jsx-dev-runtime","kind":"import-statement","external":true}],"format":"esm"},"app/routes/admin._index.tsx":{"bytes":465,"imports":[{"path":"@remix-run/node","kind":"import-statement","external":true},{"path":"@remix-run/react","kind":"import-statement","external":true},{"path":"app/components/admin/AdminDashboard.tsx","kind":"import-statement","original":"~/components/admin/AdminDashboard"},{"path":"react/jsx-dev-runtime","kind":"import-statement","external":true}],"format":"esm"},"app/components/admin/AdminOrderList.tsx":{"bytes":3923,"imports":[{"path":"react/jsx-dev-runtime","kind":"import-statement","external":true}],"format":"esm"},"app/routes/admin.orders.tsx":{"bytes":694,"imports":[{"path":"@remix-run/node","kind":"import-statement","external":true},{"path":"@remix-run/react","kind":"import-statement","external":true},{"path":"app/components/admin/AdminOrderList.tsx","kind":"import-statement","original":"~/components/admin/AdminOrderList"},{"path":"react/jsx-dev-runtime","kind":"import-statement","external":true}],"format":"esm"},"app/components/admin/RiderManagement.tsx":{"bytes":2687,"imports":[{"path":"react/jsx-dev-runtime","kind":"import-statement","external":true}],"format":"esm"},"app/routes/admin.riders.tsx":{"bytes":544,"imports":[{"path":"@remix-run/node","kind":"import-statement","external":true},{"path":"@remix-run/react","kind":"import-statement","external":true},{"path":"app/components/admin/RiderManagement.tsx","kind":"import-statement","original":"~/components/admin/RiderManagement"},{"path":"react/jsx-dev-runtime","kind":"import-statement","external":true}],"format":"esm"},"app/data/dummy.ts":{"bytes":1907,"imports":[],"format":"esm"},"app/models/product.server.ts":{"bytes":377,"imports":[{"path":"app/data/dummy.ts","kind":"import-statement","original":"~/data/dummy"}],"format":"esm"},"app/components/products/ProductCard.tsx":{"bytes":2222,"imports":[{"path":"app/lib/hooks/useCart.ts","kind":"import-statement","original":"~/lib/hooks/useCart"},{"path":"react/jsx-dev-runtime","kind":"import-statement","external":true}],"format":"esm"},"app/components/products/ProductGrid.tsx":{"bytes":319,"imports":[{"path":"app/components/products/ProductCard.tsx","kind":"import-statement","original":"./ProductCard"},{"path":"react/jsx-dev-runtime","kind":"import-statement","external":true}],"format":"esm"},"app/routes/category.$id.tsx":{"bytes":622,"imports":[{"path":"@remix-run/node","kind":"import-statement","external":true},{"path":"@remix-run/react","kind":"import-statement","external":true},{"path":"app/models/product.server.ts","kind":"import-statement","original":"~/models/product.server"},{"path":"app/components/products/ProductGrid.tsx","kind":"import-statement","original":"~/components/products/ProductGrid"},{"path":"react/jsx-dev-runtime","kind":"import-statement","external":true}],"format":"esm"},"app/components/rider/RiderDashboard.tsx":{"bytes":2628,"imports":[{"path":"react/jsx-dev-runtime","kind":"import-statement","external":true}],"format":"esm"},"app/routes/rider._index.tsx":{"bytes":516,"imports":[{"path":"@remix-run/node","kind":"import-statement","external":true},{"path":"@remix-run/react","kind":"import-statement","external":true},{"path":"app/components/rider/RiderDashboard.tsx","kind":"import-statement","original":"~/components/rider/RiderDashboard"},{"path":"react/jsx-dev-runtime","kind":"import-statement","external":true}],"format":"esm"},"app/components/categories/CategoryList.tsx":{"bytes":1243,"imports":[{"path":"react/jsx-dev-runtime","kind":"import-statement","external":true}],"format":"esm"},"app/routes/categories.tsx":{"bytes":558,"imports":[{"path":"@remix-run/node","kind":"import-statement","external":true},{"path":"@remix-run/react","kind":"import-statement","external":true},{"path":"app/components/categories/CategoryList.tsx","kind":"import-statement","original":"~/components/categories/CategoryList"},{"path":"app/data/dummy.ts","kind":"import-statement","original":"~/data/dummy"},{"path":"react/jsx-dev-runtime","kind":"import-statement","external":true}],"format":"esm"},"app/routes/checkout.tsx":{"bytes":5054,"imports":[{"path":"@remix-run/node","kind":"import-statement","external":true},{"path":"@remix-run/react","kind":"import-statement","external":true},{"path":"app/lib/hooks/useCart.ts","kind":"import-statement","original":"~/lib/hooks/useCart"},{"path":"react/jsx-dev-runtime","kind":"import-statement","external":true}],"format":"esm"},"app/routes/products.tsx":{"bytes":1008,"imports":[{"path":"@remix-run/node","kind":"import-statement","external":true},{"path":"@remix-run/react","kind":"import-statement","external":true},{"path":"app/components/products/ProductGrid.tsx","kind":"import-statement","original":"~/components/products/ProductGrid"},{"path":"app/data/dummy.ts","kind":"import-statement","original":"~/data/dummy"},{"path":"react/jsx-dev-runtime","kind":"import-statement","external":true}],"format":"esm"},"app/components/categories/CategoryBar.tsx":{"bytes":1971,"imports":[{"path":"react-i18next","kind":"import-statement","external":true},{"path":"react/jsx-dev-runtime","kind":"import-statement","external":true}],"format":"esm"},"app/components/home/HeroSection.tsx":{"bytes":2069,"imports":[{"path":"react-i18next","kind":"import-statement","external":true},{"path":"react/jsx-dev-runtime","kind":"import-statement","external":true}],"format":"esm"},"app/routes/_index.tsx":{"bytes":2468,"imports":[{"path":"@remix-run/node","kind":"import-statement","external":true},{"path":"@remix-run/react","kind":"import-statement","external":true},{"path":"react-i18next","kind":"import-statement","external":true},{"path":"app/components/categories/CategoryBar.tsx","kind":"import-statement","original":"~/components/categories/CategoryBar"},{"path":"app/components/home/HeroSection.tsx","kind":"import-statement","original":"~/components/home/HeroSection"},{"path":"app/data/dummy.ts","kind":"import-statement","original":"~/data/dummy"},{"path":"react/jsx-dev-runtime","kind":"import-statement","external":true}],"format":"esm"},"app/routes/offers.tsx":{"bytes":1562,"imports":[{"path":"@remix-run/node","kind":"import-statement","external":true},{"path":"@remix-run/react","kind":"import-statement","external":true},{"path":"react/jsx-dev-runtime","kind":"import-statement","external":true}],"format":"esm"},"app/routes/orders.tsx":{"bytes":2485,"imports":[{"path":"@remix-run/node","kind":"import-statement","external":true},{"path":"@remix-run/react","kind":"import-statement","external":true},{"path":"react/jsx-dev-runtime","kind":"import-statement","external":true}],"format":"esm"},"app/routes/search.tsx":{"bytes":1667,"imports":[{"path":"@remix-run/node","kind":"import-statement","external":true},{"path":"@remix-run/react","kind":"import-statement","external":true},{"path":"app/components/products/ProductGrid.tsx","kind":"import-statement","original":"~/components/products/ProductGrid"},{"path":"app/data/dummy.ts","kind":"import-statement","original":"~/data/dummy"},{"path":"react/jsx-dev-runtime","kind":"import-statement","external":true}],"format":"esm"},"app/routes/login.tsx":{"bytes":2001,"imports":[{"path":"@remix-run/node","kind":"import-statement","external":true},{"path":"@remix-run/react","kind":"import-statement","external":true},{"path":"react/jsx-dev-runtime","kind":"import-statement","external":true}],"format":"esm"},"app/routes/cart.tsx":{"bytes":4062,"imports":[{"path":"@remix-run/node","kind":"import-statement","external":true},{"path":"@remix-run/react","kind":"import-statement","external":true},{"path":"app/lib/hooks/useCart.ts","kind":"import-statement","original":"~/lib/hooks/useCart"},{"path":"react/jsx-dev-runtime","kind":"import-statement","external":true}],"format":"esm"},"server-assets-manifest:@remix-run/dev/assets-manifest":{"bytes":5758,"imports":[],"format":"esm"},"server-entry-module:@remix-run/dev/server-build":{"bytes":4574,"imports":[{"path":"app/entry.server.tsx","kind":"import-statement","original":"/home/projects/sb1-t7v2mxnz/app/entry.server.tsx"},{"path":"app/root.tsx","kind":"import-statement","original":"./root.tsx"},{"path":"app/routes/rider.deliveries.tsx","kind":"import-statement","original":"./routes/rider.deliveries.tsx"},{"path":"app/routes/admin.inventory.tsx","kind":"import-statement","original":"./routes/admin.inventory.tsx"},{"path":"app/routes/admin._index.tsx","kind":"import-statement","original":"./routes/admin._index.tsx"},{"path":"app/routes/admin.orders.tsx","kind":"import-statement","original":"./routes/admin.orders.tsx"},{"path":"app/routes/admin.riders.tsx","kind":"import-statement","original":"./routes/admin.riders.tsx"},{"path":"app/routes/category.$id.tsx","kind":"import-statement","original":"./routes/category.$id.tsx"},{"path":"app/routes/rider._index.tsx","kind":"import-statement","original":"./routes/rider._index.tsx"},{"path":"app/routes/categories.tsx","kind":"import-statement","original":"./routes/categories.tsx"},{"path":"app/routes/checkout.tsx","kind":"import-statement","original":"./routes/checkout.tsx"},{"path":"app/routes/products.tsx","kind":"import-statement","original":"./routes/products.tsx"},{"path":"app/routes/_index.tsx","kind":"import-statement","original":"./routes/_index.tsx"},{"path":"app/routes/offers.tsx","kind":"import-statement","original":"./routes/offers.tsx"},{"path":"app/routes/orders.tsx","kind":"import-statement","original":"./routes/orders.tsx"},{"path":"app/routes/search.tsx","kind":"import-statement","original":"./routes/search.tsx"},{"path":"app/routes/login.tsx","kind":"import-statement","original":"./routes/login.tsx"},{"path":"app/routes/cart.tsx","kind":"import-statement","original":"./routes/cart.tsx"},{"path":"server-assets-manifest:@remix-run/dev/assets-manifest","kind":"import-statement","original":"@remix-run/dev/assets-manifest"}],"format":"esm"},"<stdin>":{"bytes":44,"imports":[{"path":"server-entry-module:@remix-run/dev/server-build","kind":"import-statement","original":"@remix-run/dev/server-build"}],"format":"esm"}},"outputs":{"build/_assets/tailwind-IMNV33KW.css":{"imports":[],"exports":[],"inputs":{"app/styles/tailwind.css":{"bytesInOutput":32282}},"bytes":32282},"build/index.js.map":{"imports":[],"exports":[],"inputs":{},"bytes":134277},"build/index.js":{"imports":[{"path":"@remix-run/react","kind":"import-statement","external":true},{"path":"react-dom/server","kind":"import-statement","external":true},{"path":"react/jsx-dev-runtime","kind":"import-statement","external":true},{"path":"@remix-run/node","kind":"import-statement","external":true},{"path":"@remix-run/react","kind":"import-statement","external":true},{"path":"zustand","kind":"import-statement","external":true},{"path":"zustand/middleware","kind":"import-statement","external":true},{"path":"react","kind":"import-statement","external":true},{"path":"@remix-run/react","kind":"import-statement","external":true},{"path":"react/jsx-dev-runtime","kind":"import-statement","external":true},{"path":"react-i18next","kind":"import-statement","external":true},{"path":"react","kind":"import-statement","external":true},{"path":"react/jsx-dev-runtime","kind":"import-statement","external":true},{"path":"react-i18next","kind":"import-statement","external":true},{"path":"react/jsx-dev-runtime","kind":"import-statement","external":true},{"path":"build/_assets/tailwind-IMNV33KW.css","kind":"file-loader"},{"path":"react","kind":"import-statement","external":true},{"path":"react-i18next","kind":"import-statement","external":true},{"path":"react/jsx-dev-runtime","kind":"import-statement","external":true},{"path":"@remix-run/node","kind":"import-statement","external":true},{"path":"@remix-run/react","kind":"import-statement","external":true},{"path":"react/jsx-dev-runtime","kind":"import-statement","external":true},{"path":"react/jsx-dev-runtime","kind":"import-statement","external":true},{"path":"@remix-run/node","kind":"import-statement","external":true},{"path":"@remix-run/react","kind":"import-statement","external":true},{"path":"react","kind":"import-statement","external":true},{"path":"react/jsx-dev-runtime","kind":"import-statement","external":true},{"path":"react/jsx-dev-runtime","kind":"import-statement","external":true},{"path":"@remix-run/node","kind":"import-statement","external":true},{"path":"@remix-run/react","kind":"import-statement","external":true},{"path":"@remix-run/react","kind":"import-statement","external":true},{"path":"react/jsx-dev-runtime","kind":"import-statement","external":true},{"path":"react/jsx-dev-runtime","kind":"import-statement","external":true},{"path":"@remix-run/node","kind":"import-statement","external":true},{"path":"@remix-run/react","kind":"import-statement","external":true},{"path":"react/jsx-dev-runtime","kind":"import-statement","external":true},{"path":"react/jsx-dev-runtime","kind":"import-statement","external":true},{"path":"@remix-run/node","kind":"import-statement","external":true},{"path":"@remix-run/react","kind":"import-statement","external":true},{"path":"react/jsx-dev-runtime","kind":"import-statement","external":true},{"path":"react/jsx-dev-runtime","kind":"import-statement","external":true},{"path":"@remix-run/node","kind":"import-statement","external":true},{"path":"@remix-run/react","kind":"import-statement","external":true},{"path":"react/jsx-dev-runtime","kind":"import-statement","external":true},{"path":"react/jsx-dev-runtime","kind":"import-statement","external":true},{"path":"react/jsx-dev-runtime","kind":"import-statement","external":true},{"path":"@remix-run/node","kind":"import-statement","external":true},{"path":"@remix-run/react","kind":"import-statement","external":true},{"path":"react/jsx-dev-runtime","kind":"import-statement","external":true},{"path":"react/jsx-dev-runtime","kind":"import-statement","external":true},{"path":"@remix-run/node","kind":"import-statement","external":true},{"path":"@remix-run/react","kind":"import-statement","external":true},{"path":"react/jsx-dev-runtime","kind":"import-statement","external":true},{"path":"react/jsx-dev-runtime","kind":"import-statement","external":true},{"path":"@remix-run/node","kind":"import-statement","external":true},{"path":"react/jsx-dev-runtime","kind":"import-statement","external":true},{"path":"@remix-run/node","kind":"import-statement","external":true},{"path":"@remix-run/react","kind":"import-statement","external":true},{"path":"react/jsx-dev-runtime","kind":"import-statement","external":true},{"path":"@remix-run/node","kind":"import-statement","external":true},{"path":"@remix-run/react","kind":"import-statement","external":true},{"path":"react-i18next","kind":"import-statement","external":true},{"path":"react-i18next","kind":"import-statement","external":true},{"path":"react/jsx-dev-runtime","kind":"import-statement","external":true},{"path":"react-i18next","kind":"import-statement","external":true},{"path":"react/jsx-dev-runtime","kind":"import-statement","external":true},{"path":"react/jsx-dev-runtime","kind":"import-statement","external":true},{"path":"@remix-run/node","kind":"import-statement","external":true},{"path":"@remix-run/react","kind":"import-statement","external":true},{"path":"react/jsx-dev-runtime","kind":"import-statement","external":true},{"path":"@remix-run/node","kind":"import-statement","external":true},{"path":"@remix-run/react","kind":"import-statement","external":true},{"path":"react/jsx-dev-runtime","kind":"import-statement","external":true},{"path":"@remix-run/node","kind":"import-statement","external":true},{"path":"@remix-run/react","kind":"import-statement","external":true},{"path":"react/jsx-dev-runtime","kind":"import-statement","external":true},{"path":"@remix-run/node","kind":"import-statement","external":true},{"path":"react/jsx-dev-runtime","kind":"import-statement","external":true},{"path":"@remix-run/node","kind":"import-statement","external":true},{"path":"react/jsx-dev-runtime","kind":"import-statement","external":true}],"exports":["assets","assetsBuildDirectory","entry","future","mode","publicPath","routes"],"entryPoint":"<stdin>","inputs":{"app/entry.server.tsx":{"bytesInOutput":734},"app/root.tsx":{"bytesInOutput":2879},"app/lib/hooks/useCart.ts":{"bytesInOutput":1153},"app/components/layout/SearchBar.tsx":{"bytesInOutput":1895},"app/components/LanguageSwitcher.tsx":{"bytesInOutput":1454},"app/components/layout/Header.tsx":{"bytesInOutput":6157},"app/styles/tailwind.css":{"bytesInOutput":63},"app/routes/rider.deliveries.tsx":{"bytesInOutput":927},"app/components/rider/DeliveryHistory.tsx":{"bytesInOutput":7174},"app/routes/admin.inventory.tsx":{"bytesInOutput":1061},"app/components/admin/InventoryManagement.tsx":{"bytesInOutput":10103},"app/routes/admin._index.tsx":{"bytesInOutput":696},"app/components/admin/AdminDashboard.tsx":{"bytesInOutput":9769},"app/routes/admin.orders.tsx":{"bytesInOutput":945},"app/components/admin/AdminOrderList.tsx":{"bytesInOutput":8400},"app/routes/admin.riders.tsx":{"bytesInOutput":775},"app/components/admin/RiderManagement.tsx":{"bytesInOutput":6420},"app/routes/category.$id.tsx":{"bytesInOutput":862},"app/data/dummy.ts":{"bytesInOutput":1873},"app/models/product.server.ts":{"bytesInOutput":133},"app/components/products/ProductCard.tsx":{"bytesInOutput":4566},"app/components/products/ProductGrid.tsx":{"bytesInOutput":571},"app/routes/rider._index.tsx":{"bytesInOutput":747},"app/components/rider/RiderDashboard.tsx":{"bytesInOutput":6523},"app/routes/categories.tsx":{"bytesInOutput":1058},"app/components/categories/CategoryList.tsx":{"bytesInOutput":2279},"app/routes/checkout.tsx":{"bytesInOutput":15047},"app/routes/products.tsx":{"bytesInOutput":2588},"app/routes/_index.tsx":{"bytesInOutput":5499},"app/components/categories/CategoryBar.tsx":{"bytesInOutput":3744},"app/components/home/HeroSection.tsx":{"bytesInOutput":4314},"app/routes/offers.tsx":{"bytesInOutput":3159},"app/routes/orders.tsx":{"bytesInOutput":5748},"app/routes/search.tsx":{"bytesInOutput":2863},"app/routes/login.tsx":{"bytesInOutput":4979},"app/routes/cart.tsx":{"bytesInOutput":9978},"server-assets-manifest:@remix-run/dev/assets-manifest":{"bytesInOutput":5454},"server-entry-module:@remix-run/dev/server-build":{"bytesInOutput":3303},"<stdin>":{"bytesInOutput":0}},"bytes":147869}}}